[
  {
    "type": "dropdown-search",
    "id": "course",
    "label": "Course",
    "options": "courseList",
    "required": true
  },
  {
    "type": "date",
    "id": "start",
    "label": "Course start",
    "required": true
  },
  {
    "type": "date",
    "id": "end",
    "label": "Course end"
  },
  {
    "type": "date",
    "id": "issued",
    "label": "Certificate issued",
    "if": "id"
  },
  {
    "type": "date",
    "id": "prev_expiry",
    "label": "Previous certificate expiring date"
  },
  {
    "type": "dropdown-search",
    "id": "instructor",
    "label": "Instructor",
    "options": "instructors",
    "required": true
  }
]
